inlineplz/__init__.py
inlineplz/__main__.py
inlineplz/decorators.py
inlineplz/linter_runner.py
inlineplz/main.py
inlineplz/message.py
inlineplz/registry.py
inlineplz/bin/codenarc/CodeNarc-1.2.1.jar
inlineplz/bin/codenarc/codenarc.xml
inlineplz/bin/groovy/groovy-all-2.4.15.jar
inlineplz/bin/groovy/slf4j-api-1.7.25.jar
inlineplz/bin/pmd/pmd-bin-6.3.0/LICENSE
inlineplz/bin/pmd/pmd-bin-6.3.0/bin/bgastviewer.bat
inlineplz/bin/pmd/pmd-bin-6.3.0/bin/cpd.bat
inlineplz/bin/pmd/pmd-bin-6.3.0/bin/cpdgui.bat
inlineplz/bin/pmd/pmd-bin-6.3.0/bin/designer.bat
inlineplz/bin/pmd/pmd-bin-6.3.0/bin/pmd.bat
inlineplz/bin/pmd/pmd-bin-6.3.0/bin/run.sh
inlineplz/bin/pmd/pmd-bin-6.3.0/lib/animal-sniffer-annotations-1.14.jar
inlineplz/bin/pmd/pmd-bin-6.3.0/lib/ant-1.10.1.jar
inlineplz/bin/pmd/pmd-bin-6.3.0/lib/ant-launcher-1.10.1.jar
inlineplz/bin/pmd/pmd-bin-6.3.0/lib/antlr-runtime-3.5.2.jar
inlineplz/bin/pmd/pmd-bin-6.3.0/lib/antlr4-runtime-4.7.jar
inlineplz/bin/pmd/pmd-bin-6.3.0/lib/aopalliance-1.0.jar
inlineplz/bin/pmd/pmd-bin-6.3.0/lib/asm-6.1.1.jar
inlineplz/bin/pmd/pmd-bin-6.3.0/lib/cglib-3.2.0.jar
inlineplz/bin/pmd/pmd-bin-6.3.0/lib/commons-beanutils-core-1.8.3.jar
inlineplz/bin/pmd/pmd-bin-6.3.0/lib/commons-io-2.4.jar
inlineplz/bin/pmd/pmd-bin-6.3.0/lib/commons-lang3-3.7.jar
inlineplz/bin/pmd/pmd-bin-6.3.0/lib/commons-logging-1.1.1.jar
inlineplz/bin/pmd/pmd-bin-6.3.0/lib/controlsfx-8.40.13.jar
inlineplz/bin/pmd/pmd-bin-6.3.0/lib/error_prone_annotations-2.0.18.jar
inlineplz/bin/pmd/pmd-bin-6.3.0/lib/flowless-0.6.jar
inlineplz/bin/pmd/pmd-bin-6.3.0/lib/groovy-2.4.7.jar
inlineplz/bin/pmd/pmd-bin-6.3.0/lib/gson-2.5.jar
inlineplz/bin/pmd/pmd-bin-6.3.0/lib/guava-19.0-rc3.jar
inlineplz/bin/pmd/pmd-bin-6.3.0/lib/j2objc-annotations-1.1.jar
inlineplz/bin/pmd/pmd-bin-6.3.0/lib/javacc-5.0.jar
inlineplz/bin/pmd/pmd-bin-6.3.0/lib/javax.inject-1.jar
inlineplz/bin/pmd/pmd-bin-6.3.0/lib/jaxen-1.1.6.jar
inlineplz/bin/pmd/pmd-bin-6.3.0/lib/jcommander-1.48.jar
inlineplz-0.50.0.dist-info/AUTHORS.md
inlineplz-0.50.0.dist-info/LICENSE
inlineplz-0.50.0.dist-info/METADATA
inlineplz-0.50.0.dist-info/WHEEL
inlineplz-0.50.0.dist-info/entry_points.txt
inlineplz-0.50.0.dist-info/top_level.txt
inlineplz-0.50.0.dist-info/RECORD
