Metadata-Version: 2.1
Name: inlineplz
Version: 0.50.0
Summary: Inline your lint messages
Home-page: https://github.com/guykisel/inline-plz
Author: Guy Kisel
Author-email: guy.kisel@gmail.com
License: ISCL
Keywords: inlineplz
Platform: UNKNOWN
Classifier: Development Status :: 4 - Beta
Classifier: Intended Audience :: Developers
Classifier: License :: OSI Approved :: ISC License (ISCL)
Classifier: Natural Language :: English
Classifier: Programming Language :: Python :: 3
Classifier: Programming Language :: Python :: 3.5
Classifier: Programming Language :: Python :: 3.6
Classifier: Programming Language :: Python :: 3.7
Requires-Dist: unidiff
Requires-Dist: github3.py
Requires-Dist: xmltodict
Requires-Dist: pyyaml
Requires-Dist: scandir
Requires-Dist: uritemplate.py
Requires-Dist: dirtyjson
Requires-Dist: python-dateutil
Requires-Dist: git-url-parse
Requires-Dist: subprocess32
Requires-Dist: identify
